<?xml version="1.0" encoding="UTF-8"?>
<ehcache xmlns:xsi="http://www.w3.org/2001/XMLSchema-instance"
	xsi:noNamespaceSchemaLocation="ehcache.xsd" updateCheck="false"
	monitoring="autodetect" dynamicConfig="true">

	<diskStore path="java.io.tmpdir" />
	<!-- Default Cache configuration. These settings will be applied to caches 
		created programmatically using CacheManager.add(String cacheName). This element 
		is optional, and using CacheManager.add(String cacheName) when its not present 
		will throw CacheException The defaultCache has an implicit name "default" 
		which is a reserved cache name. -->
	<defaultCache maxEntriesLocalHeap="10000" eternal="true"
		timeToIdleSeconds="120" timeToLiveSeconds="120" diskSpoolBufferSizeMB="30"
		maxEntriesLocalDisk="10000000" diskExpiryThreadIntervalSeconds="120"
		memoryStoreEvictionPolicy="LRU" statistics="false">
		<persistence strategy="localTempSwap" />
	</defaultCache>
	
	<!--Predefined caches. Add your cache configuration settings here. If you 
		do not have a configuration for your cache a WARNING will be issued when 
		the CacheManager starts The following attributes are required for defaultCache: 
		name - Sets the name of the cache. This is used to identify the cache. It 
		must be unique. maxInMemory - Sets the maximum number of objects that will 
		be created in memory eternal - Sets whether elements are eternal. If eternal, 
		timeouts are ignored and the element is never expired. timeToIdleSeconds 
		- Sets the time to idle for an element before it expires. Is only used if 
		the element is not eternal. Idle time is now - last accessed time timeToLiveSeconds 
		- Sets the time to live for an element before it expires. Is only used if 
		the element is not eternal. TTL is now - creation time overflowToDisk - Sets 
		whether elements can overflow to disk when the in-memory cache has reached 
		the maxInMemory limit. -->
		
		
	<!-- 存储待评价信息 -->
	<cache name="waitInfo" maxEntriesLocalHeap="90000" eternal="false"
		timeToIdleSeconds="3600" timeToLiveSeconds="3600" overflowToDisk="false" />
	<!--用于提交订单时存放标示符  -->
	<cache name="submit" maxEntriesLocalHeap="90000" eternal="false"
		timeToIdleSeconds="3600" timeToLiveSeconds="3600" overflowToDisk="false" />
	
	<cache name="cache2" maxEntriesLocalHeap="9000"
		eternal="true" overflowToDisk="true" diskPersistent="true" />


	
	<!-- 以下是三个 sample cache，仅作配置参考 ============================================ -->
	<!-- Sample caches. Following are some example caches. Remove these before 
		use. -->

	<!-- Sample cache named sampleCache1 This cache contains a maximum in memory 
		of 10000 elements, and will expire an element if it is idle for more than 
		5 minutes and lives for more than 10 minutes. If there are more than 10000 
		elements it will overflow to the disk cache, which in this configuration 
		will go to wherever java.io.tmp is defined on your system. On a standard 
		Linux system this will be /tmp" -->
	<cache name="sampleCache1" maxEntriesLocalHeap="10000"
		maxEntriesLocalDisk="1000" eternal="false" diskSpoolBufferSizeMB="20"
		timeToIdleSeconds="300" timeToLiveSeconds="600"
		memoryStoreEvictionPolicy="LFU" transactionalMode="off">
		<persistence strategy="localTempSwap" />
	</cache>

	<!-- Sample cache named sampleCache2 This cache has a maximum of 1000 elements 
		in memory. There is no overflow to disk, so 1000 is also the maximum cache 
		size. Note that when a cache is eternal, timeToLive and timeToIdle are not 
		used and do not need to be specified. -->
	<cache name="sampleCache2" maxEntriesLocalHeap="1000" eternal="true"
		memoryStoreEvictionPolicy="FIFO" />

	<!-- Sample cache named sampleCache3. This cache overflows to disk. The 
		disk store is persistent between cache and VM restarts. The disk expiry thread 
		interval is set to 10 minutes, overriding the default of 2 minutes. -->
	<cache name="sampleCache3" maxEntriesLocalHeap="500" eternal="false"
		overflowToDisk="true" diskPersistent="true" timeToIdleSeconds="300"
		timeToLiveSeconds="600" diskExpiryThreadIntervalSeconds="1"
		memoryStoreEvictionPolicy="LFU">
	</cache>
	
	<!-- 缓存查询出来的评论的ID   5分钟失效-->
	<cache name="comentIds"  
	   maxElementsInMemory="100000" 
	    eternal="false" 
	    overflowToDisk="false" 
	    timeToIdleSeconds="0"  
	    timeToLiveSeconds="300"
	    memoryStoreEvictionPolicy="LFU"
	    />
	    
	<!-- 缓存查询出来每条主评的内容   永久有效-->
	<cache name="comments"  
	   maxElementsInMemory="10000" 
	    eternal="true" 
	    overflowToDisk="false" 
	    memoryStoreEvictionPolicy="FIFO"
	    />
	    <!-- 缓存每条回评的内容   永久有效-->
	<cache name="recomments"  
	   maxElementsInMemory="10000" 
	    eternal="true" 
	    overflowToDisk="false" 
	    memoryStoreEvictionPolicy="FIFO"
	    />		
	<!-- 记录点赞缓存记录   40分钟失效-->
	<cache name="praiseRecord"  
	   maxElementsInMemory="100000" 
	    eternal="false" 
	    overflowToDisk="false" 
	    timeToIdleSeconds="0"  
	    timeToLiveSeconds="2400"
	    memoryStoreEvictionPolicy="LFU"
	    />
	    <!-- 专门用于查询用户点赞记录 -->
	    <cache name="findPraise"  
	    maxElementsInMemory="100000" 
	    eternal="false" 
	    overflowToDisk="false" 
	    timeToIdleSeconds="0"  
	    timeToLiveSeconds="3600"
	    memoryStoreEvictionPolicy="LFU"
	    />
	    <!-- 专门用于记录用户自己的主回评的缓存 -->
	    <cache name="userCommentids"  
	    maxElementsInMemory="100000" 
	    eternal="false" 
	    overflowToDisk="false" 
	    timeToIdleSeconds="0"  
	    timeToLiveSeconds="300"
	    memoryStoreEvictionPolicy="LFU"
	    />
</ehcache>
